anypoint_sdk/__init__.py
anypoint_sdk/_http.py
anypoint_sdk/_logging.py
anypoint_sdk/_version.py
anypoint_sdk/auth.py
anypoint_sdk/client.py
anypoint_sdk/collectors/inventory.py
anypoint_sdk/resources/apis.py
anypoint_sdk/resources/applications.py
anypoint_sdk/resources/contracts.py
anypoint_sdk/resources/environments.py
anypoint_sdk/resources/exchange.py
anypoint_sdk/resources/groups.py
anypoint_sdk/resources/observability.py
anypoint_sdk/resources/organizations.py
anypoint_sdk/resources/policies.py
anypoint_sdk/resources/tiers.py
anypoint_sdk-0.1.0.dist-info/licenses/LICENSE
anypoint_sdk-0.1.0.dist-info/METADATA
anypoint_sdk-0.1.0.dist-info/WHEEL
anypoint_sdk-0.1.0.dist-info/top_level.txt
anypoint_sdk-0.1.0.dist-info/RECORD
