Metadata-Version: 2.4
Name: anypoint-sdk
Version: 0.1.0
Summary: SDK for MuleSoft Anypoint Platform
Author: Steve Brown
Requires-Python: >=3.10
License-File: LICENSE
Requires-Dist: requests<3.0,>=2.31
Provides-Extra: dev
Requires-Dist: types-requests; extra == "dev"
Requires-Dist: types-urllib3; extra == "dev"
Requires-Dist: coverage; extra == "dev"
Requires-Dist: mypy; extra == "dev"
Requires-Dist: black; extra == "dev"
Requires-Dist: isort; extra == "dev"
Requires-Dist: pylint; extra == "dev"
Requires-Dist: pytest; extra == "dev"
Requires-Dist: pytest-cov; extra == "dev"
Requires-Dist: build; extra == "dev"
Requires-Dist: twine; extra == "dev"
Dynamic: license-file
